schematics_xml/__init__.py
schematics_xml/models.py
schematics_xml/tests/__init__.py
schematics_xml/tests/test_models.py
schematics_xml-0.2.1.dist-info/DESCRIPTION.rst
schematics_xml-0.2.1.dist-info/METADATA
schematics_xml-0.2.1.dist-info/RECORD
schematics_xml-0.2.1.dist-info/WHEEL
schematics_xml-0.2.1.dist-info/metadata.json
schematics_xml-0.2.1.dist-info/top_level.txt
