Metadata-Version: 2.0
Name: schematics-xml
Version: 0.2.1
Summary: Python schematics models for converting to and from XML.
Home-page: http://github.com/alexhayes/schematics-xml
Author: Alex Hayes
Author-email: alex@alution.com
License: MIT
Keywords: schematics,xml,model,modelling,dicttoxml,xmltodict
Platform: any
Classifier: Development Status :: 4 - Beta
Classifier: License :: OSI Approved :: MIT License
Classifier: Topic :: Other/Nonlisted Topic
Classifier: Topic :: Software Development :: Libraries :: Python Modules
Classifier: Intended Audience :: Developers
Classifier: Programming Language :: Python
Classifier: Programming Language :: Python :: 3
Classifier: Programming Language :: Python :: 3.3
Classifier: Programming Language :: Python :: 3.4
Classifier: Programming Language :: Python :: 3.5
Classifier: Programming Language :: Python :: Implementation :: CPython
Classifier: Programming Language :: Python :: Implementation :: PyPy
Classifier: Operating System :: OS Independent
Classifier: Operating System :: POSIX
Classifier: Operating System :: Microsoft :: Windows
Classifier: Operating System :: MacOS :: MacOS X
Requires-Dist: schematics (==2.0.0a1)
Requires-Dist: lxml (==3.6.4)
Requires-Dist: xmltodict (==0.10.2)
